enconfigs/__init__.py
enconfigs/secureconfigs.py
enconfigs/tests/config/data1.yml
enconfigs/tests/config/data2.yml
enconfigs/tests/config/data3.yml
enconfigs/tests/config/.map/.data1.yml
enconfigs/tests/config/.map/.data2.yml
enconfigs/tests/config/.map/.data3.yml
enconfigs/tests/config/.metadata/.data1.yml
enconfigs/tests/config/.metadata/.data2.yml
enconfigs/tests/config/.metadata/.data3.yml
enconfigs-0.0.102.dist-info/METADATA
enconfigs-0.0.102.dist-info/WHEEL
enconfigs-0.0.102.dist-info/licenses/LICENSE
enconfigs-0.0.102.dist-info/RECORD
