Metadata-Version: 2.3
Name: enconfigs
Version: 0.0.102
Summary: Encrypt sensitive yaml/json data with user managed encryption key or a default package managed key.
Project-URL: Homepage, https://github.com/sujayy1983/Encrypted-Configs
Project-URL: Issues, https://github.com/sujayy1983/Encrypted-Configs/issues
Author-email: Sujay RS <sujayy1983@gmail.com>
License-File: LICENSE
Classifier: License :: OSI Approved :: MIT License
Classifier: Operating System :: OS Independent
Classifier: Programming Language :: Python :: 3
Requires-Python: >=3.11
Requires-Dist: cryptography>=42.0.5
Requires-Dist: pyyaml>=6.0
Requires-Dist: rich==13.3.4
